oshino_hw/__init__.py
oshino_hw/agent.py
oshino_hw/version.py
oshino_hw-0.1.3.dist-info/DESCRIPTION.rst
oshino_hw-0.1.3.dist-info/METADATA
oshino_hw-0.1.3.dist-info/RECORD
oshino_hw-0.1.3.dist-info/WHEEL
oshino_hw-0.1.3.dist-info/metadata.json
oshino_hw-0.1.3.dist-info/top_level.txt
